{
  "title": "Quail hatching ",
  "image": null,
  "configuration": {
    "description": "",
    "widgets": {
      "54126447-a441-c5bb-b4b7-f6946c0a9fd9": {
        "isSystemType": true,
        "bundleAlias": "charts",
        "typeAlias": "basic_timeseries",
        "type": "timeseries",
        "title": "Timeseries Line Chart",
        "sizeX": 16,
        "sizeY": 10,
        "row": 0,
        "col": 2,
        "config": {
          "datasources": [
            {
              "type": "entity",
              "name": null,
              "entityAliasId": "daeca1f6-58d2-da54-5cd4-7f8712e9648e",
              "filterId": null,
              "dataKeys": [
                {
                  "name": "humidity",
                  "label": "Actual Humidity",
                  "type": "timeseries",
                  "color": "#509225",
                  "settings": {
                    "showLines": true,
                    "fillLines": false,
                    "showPoints": false,
                    "showPointShape": "circle",
                    "pointShapeFormatter": "var size = radius * Math.sqrt(Math.PI) / 2;\nctx.moveTo(x - size, y - size);\nctx.lineTo(x + size, y + size);\nctx.moveTo(x - size, y + size);\nctx.lineTo(x + size, y - size);",
                    "showPointsLineWidth": 5,
                    "showPointsRadius": 3,
                    "axisPosition": "left",
                    "comparisonSettings": {
                      "showValuesForComparison": true
                    }
                  },
                  "_hash": 0.1288952112398185,
                  "units": null,
                  "decimals": null,
                  "funcBody": null,
                  "usePostProcessing": null,
                  "postFuncBody": null
                },
                {
                  "name": "max_humidity",
                  "type": "timeseries",
                  "label": "Maximal Humidity",
                  "color": "#f3cb47",
                  "settings": {
                    "excludeFromStacking": false,
                    "hideDataByDefault": false,
                    "disableDataHiding": false,
                    "removeFromLegend": false,
                    "showLines": true,
                    "fillLines": false,
                    "showPoints": false,
                    "showPointShape": "circle",
                    "pointShapeFormatter": "var size = radius * Math.sqrt(Math.PI) / 2;\nctx.moveTo(x - size, y - size);\nctx.lineTo(x + size, y + size);\nctx.moveTo(x - size, y + size);\nctx.lineTo(x + size, y - size);",
                    "showPointsLineWidth": 5,
                    "showPointsRadius": 3,
                    "showSeparateAxis": false,
                    "axisPosition": "left",
                    "thresholds": [
                      {
                        "thresholdValueSource": "predefinedValue"
                      }
                    ],
                    "comparisonSettings": {
                      "showValuesForComparison": true
                    }
                  },
                  "_hash": 0.12032382361566385,
                  "units": null,
                  "decimals": null,
                  "funcBody": null,
                  "usePostProcessing": null,
                  "postFuncBody": null
                },
                {
                  "name": "min_humidity",
                  "type": "timeseries",
                  "label": "Minimum Humidity",
                  "color": "#d43c13",
                  "settings": {
                    "excludeFromStacking": false,
                    "hideDataByDefault": false,
                    "disableDataHiding": false,
                    "removeFromLegend": false,
                    "showLines": true,
                    "fillLines": false,
                    "showPoints": false,
                    "showPointShape": "circle",
                    "pointShapeFormatter": "var size = radius * Math.sqrt(Math.PI) / 2;\nctx.moveTo(x - size, y - size);\nctx.lineTo(x + size, y + size);\nctx.moveTo(x - size, y + size);\nctx.lineTo(x + size, y - size);",
                    "showPointsLineWidth": 5,
                    "showPointsRadius": 3,
                    "showSeparateAxis": false,
                    "axisPosition": "left",
                    "thresholds": [
                      {
                        "thresholdValueSource": "predefinedValue"
                      }
                    ],
                    "comparisonSettings": {
                      "showValuesForComparison": true
                    }
                  },
                  "_hash": 0.9546627685973053,
                  "units": null,
                  "decimals": null,
                  "funcBody": null,
                  "usePostProcessing": null,
                  "postFuncBody": null
                }
              ]
            }
          ],
          "timewindow": {
            "realtime": {
              "timewindowMs": 60000
            }
          },
          "showTitle": true,
          "backgroundColor": "#fff",
          "color": "rgba(0, 0, 0, 0.87)",
          "padding": "8px",
          "settings": {
            "shadowSize": 4,
            "fontColor": "#545454",
            "fontSize": 10,
            "xaxis": {
              "showLabels": true,
              "color": "#545454"
            },
            "yaxis": {
              "showLabels": true,
              "color": "#545454",
              "max": 85,
              "tickDecimals": 0,
              "min": 30
            },
            "grid": {
              "color": "#545454",
              "tickColor": "#DDDDDD",
              "verticalLines": true,
              "horizontalLines": true,
              "outlineWidth": 1
            },
            "stack": false,
            "tooltipIndividual": false,
            "timeForComparison": "days",
            "xaxisSecond": {
              "axisPosition": "top",
              "showLabels": true
            },
            "comparisonEnabled": false,
            "customLegendEnabled": false,
            "hideZeros": true,
            "smoothLines": true
          },
          "title": "Timeseries Line Chart of HUMIDITY",
          "dropShadow": true,
          "enableFullscreen": true,
          "titleStyle": {
            "fontSize": "16px",
            "fontWeight": 400
          },
          "mobileHeight": null,
          "useDashboardTimewindow": true,
          "showTitleIcon": false,
          "iconColor": "rgba(0, 0, 0, 0.87)",
          "iconSize": "24px",
          "titleTooltip": "",
          "widgetStyle": {},
          "showLegend": true,
          "legendConfig": {
            "direction": "row",
            "position": "bottom",
            "sortDataKeys": false,
            "showMin": false,
            "showMax": false,
            "showAvg": false,
            "showTotal": false
          }
        },
        "id": "54126447-a441-c5bb-b4b7-f6946c0a9fd9"
      },
      "07d9f712-0c23-1c05-6fce-dbd42094dd0d": {
        "isSystemType": true,
        "bundleAlias": "charts",
        "typeAlias": "basic_timeseries",
        "type": "timeseries",
        "title": "Timeseries Line Chart",
        "sizeX": 16,
        "sizeY": 10,
        "row": 0,
        "col": 2,
        "config": {
          "datasources": [
            {
              "type": "entity",
              "name": null,
              "entityAliasId": "daeca1f6-58d2-da54-5cd4-7f8712e9648e",
              "filterId": null,
              "dataKeys": [
                {
                  "name": "temperature",
                  "label": "Actual Temperature",
                  "type": "timeseries",
                  "color": "#509225",
                  "settings": {
                    "showLines": true,
                    "fillLines": false,
                    "showPoints": false,
                    "showPointShape": "circle",
                    "pointShapeFormatter": "var size = radius * Math.sqrt(Math.PI) / 2;\nctx.moveTo(x - size, y - size);\nctx.lineTo(x + size, y + size);\nctx.moveTo(x - size, y + size);\nctx.lineTo(x + size, y - size);",
                    "showPointsLineWidth": 5,
                    "showPointsRadius": 3,
                    "axisPosition": "left",
                    "comparisonSettings": {
                      "showValuesForComparison": true
                    }
                  },
                  "_hash": 0.8397940155998715,
                  "units": null,
                  "decimals": 1,
                  "funcBody": null,
                  "usePostProcessing": false,
                  "postFuncBody": null
                },
                {
                  "name": "max_temperature",
                  "type": "timeseries",
                  "label": "Maximal Temperature",
                  "color": "#d43c13",
                  "settings": {
                    "excludeFromStacking": false,
                    "hideDataByDefault": false,
                    "disableDataHiding": false,
                    "removeFromLegend": false,
                    "showLines": true,
                    "fillLines": false,
                    "showPoints": false,
                    "showPointShape": "circle",
                    "pointShapeFormatter": "var size = radius * Math.sqrt(Math.PI) / 2;\nctx.moveTo(x - size, y - size);\nctx.lineTo(x + size, y + size);\nctx.moveTo(x - size, y + size);\nctx.lineTo(x + size, y - size);",
                    "showPointsLineWidth": 5,
                    "showPointsRadius": 3,
                    "showSeparateAxis": false,
                    "axisPosition": "left",
                    "thresholds": [
                      {
                        "thresholdValueSource": "predefinedValue"
                      }
                    ],
                    "comparisonSettings": {
                      "showValuesForComparison": true
                    }
                  },
                  "_hash": 0.908299896430047,
                  "units": null,
                  "decimals": 1,
                  "funcBody": null,
                  "usePostProcessing": null,
                  "postFuncBody": null
                },
                {
                  "name": "min_temperature",
                  "type": "timeseries",
                  "label": "Minimal Temperature",
                  "color": "#f3cb47",
                  "settings": {
                    "excludeFromStacking": false,
                    "hideDataByDefault": false,
                    "disableDataHiding": false,
                    "removeFromLegend": false,
                    "showLines": true,
                    "fillLines": false,
                    "showPoints": false,
                    "showPointShape": "circle",
                    "pointShapeFormatter": "var size = radius * Math.sqrt(Math.PI) / 2;\nctx.moveTo(x - size, y - size);\nctx.lineTo(x + size, y + size);\nctx.moveTo(x - size, y + size);\nctx.lineTo(x + size, y - size);",
                    "showPointsLineWidth": 5,
                    "showPointsRadius": 3,
                    "showSeparateAxis": false,
                    "axisPosition": "left",
                    "thresholds": [
                      {
                        "thresholdValueSource": "predefinedValue"
                      }
                    ],
                    "comparisonSettings": {
                      "showValuesForComparison": true
                    }
                  },
                  "_hash": 0.28493582527520944,
                  "units": null,
                  "decimals": null,
                  "funcBody": null,
                  "usePostProcessing": null,
                  "postFuncBody": null
                }
              ]
            }
          ],
          "timewindow": {
            "realtime": {
              "timewindowMs": 60000
            }
          },
          "showTitle": true,
          "backgroundColor": "#ffffff",
          "color": "rgba(0, 0, 0, 0.87)",
          "padding": "8px",
          "settings": {
            "shadowSize": 4,
            "fontColor": "#545454",
            "fontSize": 10,
            "xaxis": {
              "showLabels": true,
              "color": "#545454"
            },
            "yaxis": {
              "showLabels": true,
              "color": "#545454",
              "tickDecimals": 1,
              "max": 39,
              "min": 34
            },
            "grid": {
              "color": "#545454",
              "tickColor": "#DDDDDD",
              "verticalLines": true,
              "horizontalLines": true,
              "outlineWidth": 1
            },
            "stack": false,
            "tooltipIndividual": false,
            "timeForComparison": "previousInterval",
            "xaxisSecond": {
              "axisPosition": "top",
              "showLabels": true
            },
            "smoothLines": true
          },
          "title": "Timeseries Line Chart of TEMPERATURE",
          "dropShadow": true,
          "enableFullscreen": true,
          "titleStyle": {
            "fontSize": "16px",
            "fontWeight": 400
          },
          "mobileHeight": null,
          "showTitleIcon": false,
          "iconColor": "rgba(0, 0, 0, 0.87)",
          "iconSize": "24px",
          "titleTooltip": "",
          "widgetStyle": {},
          "showLegend": true,
          "legendConfig": {
            "direction": "row",
            "position": "bottom",
            "sortDataKeys": false,
            "showMin": false,
            "showMax": false,
            "showAvg": false,
            "showTotal": false
          },
          "useDashboardTimewindow": true
        },
        "id": "07d9f712-0c23-1c05-6fce-dbd42094dd0d"
      },
      "723fd1dd-6329-57d1-916c-4544746a1b4c": {
        "isSystemType": true,
        "bundleAlias": "cards",
        "typeAlias": "html_card",
        "type": "static",
        "title": "New widget",
        "sizeX": 12,
        "sizeY": 10,
        "config": {
          "datasources": [],
          "timewindow": {
            "realtime": {
              "timewindowMs": 60000
            }
          },
          "showTitle": true,
          "backgroundColor": "#ffffff",
          "color": "rgba(0, 0, 0, 0.87)",
          "padding": "8px",
          "settings": {
            "cardCss": ".card {\n    font-weight: bold;\n    font-size: 32px;\n    color: black;\n    width: 100%;\n    height: 100%;\n    /*display: flex;\n    flex-direction: column; */\n    align-items: center;\n    justify-content: center;\n}\n\n.video{\n    height: 100%;\n    width: 100%;\n    margin: auto;\n}",
            "cardHtml": "<iframe width=\"100%\" height=\"100%\" src=\"https://www.youtube.com/embed/X25GNIiIHBY\" title=\"YouTube video player\" frameborder=\"0\" allow=\"accelerometer; autoplay; clipboard-write; encrypted-media; gyroscope; picture-in-picture\" allowfullscreen></iframe>"
          },
          "title": "Live Stream",
          "dropShadow": true,
          "enableFullscreen": true,
          "widgetStyle": {},
          "titleStyle": {
            "fontSize": "16px",
            "fontWeight": 400
          },
          "useDashboardTimewindow": true,
          "showLegend": false,
          "actions": {},
          "showTitleIcon": false,
          "iconColor": "rgba(0, 0, 0, 0.87)",
          "iconSize": "24px",
          "titleTooltip": ""
        },
        "id": "723fd1dd-6329-57d1-916c-4544746a1b4c"
      },
      "da57e810-e324-1659-b5da-ccfee47676d5": {
        "isSystemType": true,
        "bundleAlias": "cards",
        "typeAlias": "simple_card",
        "type": "latest",
        "title": "New widget",
        "image": null,
        "description": null,
        "sizeX": 5,
        "sizeY": 3,
        "config": {
          "datasources": [
            {
              "type": "entity",
              "name": null,
              "entityAliasId": "daeca1f6-58d2-da54-5cd4-7f8712e9648e",
              "filterId": null,
              "dataKeys": [
                {
                  "name": "humidity",
                  "type": "timeseries",
                  "label": "Humidity",
                  "color": "#2196f3",
                  "settings": {},
                  "_hash": 0.3301434550732738,
                  "units": null,
                  "decimals": null,
                  "funcBody": null,
                  "usePostProcessing": null,
                  "postFuncBody": null
                }
              ]
            }
          ],
          "timewindow": {
            "realtime": {
              "timewindowMs": 60000
            }
          },
          "showTitle": false,
          "backgroundColor": "#31badf",
          "color": "rgba(255, 255, 255, 0.87)",
          "padding": "16px",
          "settings": {
            "labelPosition": "top"
          },
          "title": "New Simple card",
          "dropShadow": true,
          "enableFullscreen": true,
          "titleStyle": {
            "fontSize": "16px",
            "fontWeight": 400
          },
          "units": "%",
          "decimals": 0,
          "useDashboardTimewindow": true,
          "showLegend": false,
          "widgetStyle": {},
          "actions": {},
          "showTitleIcon": false,
          "iconColor": "rgba(0, 0, 0, 0.87)",
          "iconSize": "24px",
          "titleTooltip": ""
        },
        "row": 0,
        "col": 0,
        "id": "da57e810-e324-1659-b5da-ccfee47676d5"
      },
      "af9ca5ec-b1cc-37cc-c7b6-69ba590cc915": {
        "isSystemType": true,
        "bundleAlias": "cards",
        "typeAlias": "simple_card",
        "type": "latest",
        "title": "New widget",
        "image": null,
        "description": null,
        "sizeX": 5,
        "sizeY": 3,
        "config": {
          "datasources": [
            {
              "type": "entity",
              "name": null,
              "entityAliasId": "daeca1f6-58d2-da54-5cd4-7f8712e9648e",
              "filterId": null,
              "dataKeys": [
                {
                  "name": "temperature",
                  "type": "timeseries",
                  "label": "Temperature",
                  "color": "#2196f3",
                  "settings": {},
                  "_hash": 0.04579440304700566,
                  "units": null,
                  "decimals": 1,
                  "funcBody": null,
                  "usePostProcessing": null,
                  "postFuncBody": null
                }
              ]
            }
          ],
          "timewindow": {
            "realtime": {
              "timewindowMs": 60000
            }
          },
          "showTitle": false,
          "backgroundColor": "#f27c3f",
          "color": "rgba(255, 255, 255, 0.87)",
          "padding": "16px",
          "settings": {
            "labelPosition": "top"
          },
          "title": "New Simple card",
          "dropShadow": true,
          "enableFullscreen": true,
          "titleStyle": {
            "fontSize": "16px",
            "fontWeight": 400
          },
          "units": "°C",
          "decimals": 0,
          "useDashboardTimewindow": true,
          "showLegend": false,
          "widgetStyle": {},
          "actions": {},
          "showTitleIcon": false,
          "iconColor": "rgba(0, 0, 0, 0.87)",
          "iconSize": "24px",
          "titleTooltip": ""
        },
        "row": 0,
        "col": 0,
        "id": "af9ca5ec-b1cc-37cc-c7b6-69ba590cc915"
      },
      "875a3c70-13c8-0784-af46-75a3f7b0de37": {
        "isSystemType": true,
        "bundleAlias": "cards",
        "typeAlias": "html_card",
        "type": "static",
        "title": "New widget",
        "image": null,
        "description": null,
        "sizeX": 7.5,
        "sizeY": 3,
        "config": {
          "datasources": [],
          "timewindow": {
            "realtime": {
              "timewindowMs": 60000
            }
          },
          "showTitle": false,
          "backgroundColor": "rgb(255, 255, 255)",
          "color": "rgba(0, 0, 0, 0.87)",
          "padding": "",
          "settings": {
            "cardHtml": "<div class='card' style=\"font-size:2vw\">\n    <h2>Welcome friend!</h2>\n    <p>Here you can see livestream and temperature and humidity sensor data from our hatchery where we have quail's eggs.</p>\n    <p class=\"bold\">Baby quails will be born in</p><!-- Display the countdown timer in an element -->\n<p id=\"demo\" class=\"demo\" ></p>\n\n<script>\n// Set the date we're counting down to\nvar countDownDate = new Date(\"Apr 21, 2021 15:00:00\").getTime();\n\n// Update the count down every 1 second\nvar x = setInterval(function() {\n\n  // Get today's date and time\n  var now = new Date().getTime();\n\n  // Find the distance between now and the count down date\n  var distance = countDownDate - now;\n\n  // Time calculations for days, hours, minutes and seconds\n  var days = Math.floor(distance / (1000 * 60 * 60 * 24));\n  var hours = Math.floor((distance % (1000 * 60 * 60 * 24)) / (1000 * 60 * 60));\n  var minutes = Math.floor((distance % (1000 * 60 * 60)) / (1000 * 60));\n  var seconds = Math.floor((distance % (1000 * 60)) / 1000);\n\n  // Display the result in the element with id=\"demo\"\n  document.getElementById(\"demo\").innerHTML = days + \"d \" + hours + \"h \"\n  + minutes + \"m \" + seconds + \"s \";\n\n  // If the count down is finished, write some text\n  if (distance < 0) {\n    clearInterval(x);\n    document.getElementById(\"demo\").innerHTML = \"Timed out, It's there!\";\n  }\n}, 1000);\n</script>\n</div>",
            "cardCss": ".card {\n    font-weight: normal;\n    color: #545454;\n    width: 100%;\n    height: 100%;\n    align-items: center;\n    justify-content: center;\n}\n\np, h2{\n    text-align: center;\n    \n}\n\np.bold, p.demo{\n    font-weight:bold !important;\n}\n\n p.demo{\n    color: #305680;\n    margin: 0 !important;\n}\n"
          },
          "title": "New HTML Card",
          "dropShadow": true,
          "showTitleIcon": false,
          "iconColor": "rgba(0, 0, 0, 0.87)",
          "iconSize": "24px",
          "titleTooltip": "",
          "enableFullscreen": true,
          "margin": "",
          "widgetStyle": {},
          "titleStyle": {
            "fontSize": "16px",
            "fontWeight": 400
          },
          "showLegend": false
        },
        "row": 0,
        "col": 0,
        "id": "875a3c70-13c8-0784-af46-75a3f7b0de37"
      }
    },
    "states": {
      "default": {
        "name": "KateRPiProject",
        "root": true,
        "layouts": {
          "main": {
            "widgets": {
              "54126447-a441-c5bb-b4b7-f6946c0a9fd9": {
                "sizeX": 11,
                "sizeY": 5,
                "mobileHeight": null,
                "row": 6,
                "col": 12
              },
              "07d9f712-0c23-1c05-6fce-dbd42094dd0d": {
                "sizeX": 11,
                "sizeY": 5,
                "mobileHeight": null,
                "row": 6,
                "col": 1
              },
              "723fd1dd-6329-57d1-916c-4544746a1b4c": {
                "sizeX": 9,
                "sizeY": 6,
                "row": 0,
                "col": 6
              },
              "da57e810-e324-1659-b5da-ccfee47676d5": {
                "sizeX": 5,
                "sizeY": 3,
                "row": 3,
                "col": 1
              },
              "af9ca5ec-b1cc-37cc-c7b6-69ba590cc915": {
                "sizeX": 5,
                "sizeY": 3,
                "row": 0,
                "col": 1
              },
              "875a3c70-13c8-0784-af46-75a3f7b0de37": {
                "sizeX": 8,
                "sizeY": 6,
                "row": 0,
                "col": 15
              }
            },
            "gridSettings": {
              "backgroundColor": "rgba(63,59,59,0.21)",
              "color": "rgba(0,0,0,0.870588)",
              "columns": 24,
              "margin": 10,
              "backgroundSizeMode": "100%",
              "autoFillHeight": false,
              "backgroundImageUrl": null,
              "mobileAutoFillHeight": false,
              "mobileRowHeight": 70
            }
          }
        }
      }
    },
    "entityAliases": {
      "daeca1f6-58d2-da54-5cd4-7f8712e9648e": {
        "id": "daeca1f6-58d2-da54-5cd4-7f8712e9648e",
        "alias": "BME280 Sensor",
        "filter": {
          "type": "singleEntity",
          "singleEntity": {
            "entityType": "DEVICE",
            "id": "da56c400-939d-11eb-9587-b30e83eb6bf1"
          },
          "resolveMultiple": false
        }
      }
    },
    "filters": {},
    "timewindow": {
      "hideInterval": false,
      "hideAggregation": false,
      "hideAggInterval": false,
      "hideTimezone": false,
      "selectedTab": 0,
      "realtime": {
        "realtimeType": 0,
        "timewindowMs": 36000000,
        "quickInterval": "CURRENT_DAY",
        "interval": 120000
      },
      "aggregation": {
        "type": "AVG",
        "limit": 2500
      }
    },
    "settings": {
      "stateControllerId": "entity",
      "showTitle": false,
      "showDashboardsSelect": true,
      "showEntitiesSelect": true,
      "showDashboardTimewindow": true,
      "showDashboardExport": true,
      "toolbarAlwaysOpen": true,
      "titleColor": "rgba(0,0,0,0.870588)",
      "showFilters": true,
      "showDashboardLogo": false,
      "dashboardLogoUrl": null
    }
  },
  "name": "Quail hatching "
}